netcm/__init__.py
netcm/models/__init__.py
netcm/models/BaseModels/BaseNetCmModel.py
netcm/models/BaseModels/SharedModels.py
netcm/models/BaseModels/__init__.py
netcm/models/Fields/Fields.py
netcm/models/Fields/__init__.py
netcm/models/VendorIndependent/VlanModel.py
netcm/models/VendorIndependent/__init__.py
netcm/models/interfaces/__init__.py
netcm/models/interfaces/vi/InterfaceModels.py
netcm/models/interfaces/vi/L2InterfaceModels.py
netcm/models/interfaces/vi/L3InterfaceModels.py
netcm/models/interfaces/vi/__init__.py
netcm/models/routing/__init__.py
netcm/models/routing/vi/BgpModels.py
netcm/models/routing/vi/RoutingProtocolBase.py
netcm/models/routing/vi/RoutingProtocols.py
netcm/models/routing/vi/StaticRoutes.py
netcm/models/routing/vi/__init__.py
netcm/models/services/__init__.py
netcm/models/services/vi/ServerModels.py
netcm/models/services/vi/__init__.py
netcm/utils/CustomYamlDumper.py
netcm/utils/__init__.py
netcm/utils/common.py
netcm/utils/get_logger.py
netcm/utils/interface_sort.py
netcm/validators/__init__.py
netcm/validators/validators.py
netcm-0.1.2.dist-info/LICENSE
netcm-0.1.2.dist-info/METADATA
netcm-0.1.2.dist-info/WHEEL
netcm-0.1.2.dist-info/top_level.txt
netcm-0.1.2.dist-info/RECORD
